companion_template/__init__.py
companion_template/builder.py
companion_template/template_types.py
companion_template-0.1.5.dist-info/METADATA
companion_template-0.1.5.dist-info/WHEEL
companion_template-0.1.5.dist-info/top_level.txt
companion_template-0.1.5.dist-info/RECORD
