Metadata-Version: 2.1
Name: companion-template
Version: 0.1.5
Classifier: Programming Language :: Python :: 3
Requires-Python: >=3.9
Requires-Dist: toml
